verilog003/FSM_analise.v

module FSM_analise (
    reset,
    cnt,
    clock,
    y
);
    // entradas
    input reset;
    input cnt;
    input clock;
    output y;

    reg[1:0] registrador;
    wire[1:0] fio;

    assign fio[0] = registrador[0] ^ cnt;
    assign fio[1] = registrador[1] & ~cnt | registrador[0] & cnt & ~registrador[1] | registrador[1] & ~registrador[0];
    assign y = registrador[0] & registrador[1];

    always @(posedge clock or reset ) begin
        if(reset == 1) registrador = 0;
        else registrador = fio;
    end

endmodule


module testbench;

    reg cnt0 = 0;
    reg reset0 = 0;
    reg clock0 = 0;
    wire y0;

    FSM_analise FSM0(reset0, cnt0, clock0, y0);
    
    always #1 begin
        clock0<=~clock0;
    end 

    initial begin
        $dumpvars;
        #1 
        reset0 = 1;
        #1
        reset0 = 0;
        #1
        cnt0 = 1;
        #500
        $finish;
    end

endmodule

verilog003/dump.vcd
$date
	Fri Jul 01 09:31:21 2022
$end
$version
	Icarus Verilog
$end
$timescale
	1s
$end
$scope module testbench $end
$var wire 1 ! y0 $end
$var reg 1 " clock0 $end
$var reg 1 # cnt0 $end
$var reg 1 $ reset0 $end
$scope module FSM0 $end
$var wire 1 " clock $end
$var wire 1 # cnt $end
$var wire 1 $ reset $end
$var wire 1 ! y $end
$var wire 2 % fio [1:0] $end
$var reg 2 & registrador [1:0] $end
$upscope $end
$upscope $end
$enddefinitions $end
$comment Show the parameter values. $end
$dumpall
$end
#0
$dumpvars
bx &
bx %
0$
0#
0"
x!
$end
#1
1"
b0 %
0!
b0 &
1$
#2
0"
0$
#3
b1 &
1"
b10 %
1#
#4
0"
#5
b11 %
b10 &
1"
#6
0"
#7
b0 %
1!
b11 &
1"
#8
0"
#9
b1 %
0!
b0 &
1"
#10
0"
#11
b10 %
b1 &
1"
#12
0"
#13
b11 %
b10 &
1"
#14
0"
#15
b0 %
1!
b11 &
1"
#16
0"
#17
b1 %
0!
b0 &
1"
#18
0"
#19
b10 %
b1 &
1"
#20
0"
#21
b11 %
b10 &
1"
#22
0"
#23
b0 %
1!
b11 &
1"
#24
0"
#25
b1 %
0!
b0 &
1"
#26
0"
#27
b10 %
b1 &
1"
#28
0"
#29
b11 %
b10 &
1"
#30
0"
#31
b0 %
1!
b11 &
1"
#32
0"
#33
b1 %
0!
b0 &
1"
#34
0"
#35
b10 %
b1 &
1"
#36
0"
#37
b11 %
b10 &
1"
#38
0"
#39
b0 %
1!
b11 &
1"
#40
0"
#41
b1 %
0!
b0 &
1"
#42
0"
#43
b10 %
b1 &
1"
#44
0"
#45
b11 %
b10 &
1"
#46
0"
#47
b0 %
1!
b11 &
1"
#48
0"
#49
b1 %
0!
b0 &
1"
#50
0"
#51
b10 %
b1 &
1"
#52
0"
#53
b11 %
b10 &
1"
#54
0"
#55
b0 %
1!
b11 &
1"
#56
0"
#57
b1 %
0!
b0 &
1"
#58
0"
#59
b10 %
b1 &
1"
#60
0"
#61
b11 %
b10 &
1"
#62
0"
#63
b0 %
1!
b11 &
1"
#64
0"
#65
b1 %
0!
b0 &
1"
#66
0"
#67
b10 %
b1 &
1"
#68
0"
#69
b11 %
b10 &
1"
#70
0"
#71
b0 %
1!
b11 &
1"
#72
0"
#73
b1 %
0!
b0 &
1"
#74
0"
#75
b10 %
b1 &
1"
#76
0"
#77
b11 %
b10 &
1"
#78
0"
#79
b0 %
1!
b11 &
1"
#80
0"
#81
b1 %
0!
b0 &
1"
#82
0"
#83
b10 %
b1 &
1"
#84
0"
#85
b11 %
b10 &
1"
#86
0"
#87
b0 %
1!
b11 &
1"
#88
0"
#89
b1 %
0!
b0 &
1"
#90
0"
#91
b10 %
b1 &
1"
#92
0"
#93
b11 %
b10 &
1"
#94
0"
#95
b0 %
1!
b11 &
1"
#96
0"
#97
b1 %
0!
b0 &
1"
#98
0"
#99
b10 %
b1 &
1"
#100
0"
#101
b11 %
b10 &
1"
#102
0"
#103
b0 %
1!
b11 &
1"
#104
0"
#105
b1 %
0!
b0 &
1"
#106
0"
#107
b10 %
b1 &
1"
#108
0"
#109
b11 %
b10 &
1"
#110
0"
#111
b0 %
1!
b11 &
1"
#112
0"
#113
b1 %
0!
b0 &
1"
#114
0"
#115
b10 %
b1 &
1"
#116
0"
#117
b11 %
b10 &
1"
#118
0"
#119
b0 %
1!
b11 &
1"
#120
0"
#121
b1 %
0!
b0 &
1"
#122
0"
#123
b10 %
b1 &
1"
#124
0"
#125
b11 %
b10 &
1"
#126
0"
#127
b0 %
1!
b11 &
1"
#128
0"
#129
b1 %
0!
b0 &
1"
#130
0"
#131
b10 %
b1 &
1"
#132
0"
#133
b11 %
b10 &
1"
#134
0"
#135
b0 %
1!
b11 &
1"
#136
0"
#137
b1 %
0!
b0 &
1"
#138
0"
#139
b10 %
b1 &
1"
#140
0"
#141
b11 %
b10 &
1"
#142
0"
#143
b0 %
1!
b11 &
1"
#144
0"
#145
b1 %
0!
b0 &
1"
#146
0"
#147
b10 %
b1 &
1"
#148
0"
#149
b11 %
b10 &
1"
#150
0"
#151
b0 %
1!
b11 &
1"
#152
0"
#153
b1 %
0!
b0 &
1"
#154
0"
#155
b10 %
b1 &
1"
#156
0"
#157
b11 %
b10 &
1"
#158
0"
#159
b0 %
1!
b11 &
1"
#160
0"
#161
b1 %
0!
b0 &
1"
#162
0"
#163
b10 %
b1 &
1"
#164
0"
#165
b11 %
b10 &
1"
#166
0"
#167
b0 %
1!
b11 &
1"
#168
0"
#169
b1 %
0!
b0 &
1"
#170
0"
#171
b10 %
b1 &
1"
#172
0"
#173
b11 %
b10 &
1"
#174
0"
#175
b0 %
1!
b11 &
1"
#176
0"
#177
b1 %
0!
b0 &
1"
#178
0"
#179
b10 %
b1 &
1"
#180
0"
#181
b11 %
b10 &
1"
#182
0"
#183
b0 %
1!
b11 &
1"
#184
0"
#185
b1 %
0!
b0 &
1"
#186
0"
#187
b10 %
b1 &
1"
#188
0"
#189
b11 %
b10 &
1"
#190
0"
#191
b0 %
1!
b11 &
1"
#192
0"
#193
b1 %
0!
b0 &
1"
#194
0"
#195
b10 %
b1 &
1"
#196
0"
#197
b11 %
b10 &
1"
#198
0"
#199
b0 %
1!
b11 &
1"
#200
0"
#201
b1 %
0!
b0 &
1"
#202
0"
#203
b10 %
b1 &
1"
#204
0"
#205
b11 %
b10 &
1"
#206
0"
#207
b0 %
1!
b11 &
1"
#208
0"
#209
b1 %
0!
b0 &
1"
#210
0"
#211
b10 %
b1 &
1"
#212
0"
#213
b11 %
b10 &
1"
#214
0"
#215
b0 %
1!
b11 &
1"
#216
0"
#217
b1 %
0!
b0 &
1"
#218
0"
#219
b10 %
b1 &
1"
#220
0"
#221
b11 %
b10 &
1"
#222
0"
#223
b0 %
1!
b11 &
1"
#224
0"
#225
b1 %
0!
b0 &
1"
#226
0"
#227
b10 %
b1 &
1"
#228
0"
#229
b11 %
b10 &
1"
#230
0"
#231
b0 %
1!
b11 &
1"
#232
0"
#233
b1 %
0!
b0 &
1"
#234
0"
#235
b10 %
b1 &
1"
#236
0"
#237
b11 %
b10 &
1"
#238
0"
#239
b0 %
1!
b11 &
1"
#240
0"
#241
b1 %
0!
b0 &
1"
#242
0"
#243
b10 %
b1 &
1"
#244
0"
#245
b11 %
b10 &
1"
#246
0"
#247
b0 %
1!
b11 &
1"
#248
0"
#249
b1 %
0!
b0 &
1"
#250
0"
#251
b10 %
b1 &
1"
#252
0"
#253
b11 %
b10 &
1"
#254
0"
#255
b0 %
1!
b11 &
1"
#256
0"
#257
b1 %
0!
b0 &
1"
#258
0"
#259
b10 %
b1 &
1"
#260
0"
#261
b11 %
b10 &
1"
#262
0"
#263
b0 %
1!
b11 &
1"
#264
0"
#265
b1 %
0!
b0 &
1"
#266
0"
#267
b10 %
b1 &
1"
#268
0"
#269
b11 %
b10 &
1"
#270
0"
#271
b0 %
1!
b11 &
1"
#272
0"
#273
b1 %
0!
b0 &
1"
#274
0"
#275
b10 %
b1 &
1"
#276
0"
#277
b11 %
b10 &
1"
#278
0"
#279
b0 %
1!
b11 &
1"
#280
0"
#281
b1 %
0!
b0 &
1"
#282
0"
#283
b10 %
b1 &
1"
#284
0"
#285
b11 %
b10 &
1"
#286
0"
#287
b0 %
1!
b11 &
1"
#288
0"
#289
b1 %
0!
b0 &
1"
#290
0"
#291
b10 %
b1 &
1"
#292
0"
#293
b11 %
b10 &
1"
#294
0"
#295
b0 %
1!
b11 &
1"
#296
0"
#297
b1 %
0!
b0 &
1"
#298
0"
#299
b10 %
b1 &
1"
#300
0"
#301
b11 %
b10 &
1"
#302
0"
#303
b0 %
1!
b11 &
1"
#304
0"
#305
b1 %
0!
b0 &
1"
#306
0"
#307
b10 %
b1 &
1"
#308
0"
#309
b11 %
b10 &
1"
#310
0"
#311
b0 %
1!
b11 &
1"
#312
0"
#313
b1 %
0!
b0 &
1"
#314
0"
#315
b10 %
b1 &
1"
#316
0"
#317
b11 %
b10 &
1"
#318
0"
#319
b0 %
1!
b11 &
1"
#320
0"
#321
b1 %
0!
b0 &
1"
#322
0"
#323
b10 %
b1 &
1"
#324
0"
#325
b11 %
b10 &
1"
#326
0"
#327
b0 %
1!
b11 &
1"
#328
0"
#329
b1 %
0!
b0 &
1"
#330
0"
#331
b10 %
b1 &
1"
#332
0"
#333
b11 %
b10 &
1"
#334
0"
#335
b0 %
1!
b11 &
1"
#336
0"
#337
b1 %
0!
b0 &
1"
#338
0"
#339
b10 %
b1 &
1"
#340
0"
#341
b11 %
b10 &
1"
#342
0"
#343
b0 %
1!
b11 &
1"
#344
0"
#345
b1 %
0!
b0 &
1"
#346
0"
#347
b10 %
b1 &
1"
#348
0"
#349
b11 %
b10 &
1"
#350
0"
#351
b0 %
1!
b11 &
1"
#352
0"
#353
b1 %
0!
b0 &
1"
#354
0"
#355
b10 %
b1 &
1"
#356
0"
#357
b11 %
b10 &
1"
#358
0"
#359
b0 %
1!
b11 &
1"
#360
0"
#361
b1 %
0!
b0 &
1"
#362
0"
#363
b10 %
b1 &
1"
#364
0"
#365
b11 %
b10 &
1"
#366
0"
#367
b0 %
1!
b11 &
1"
#368
0"
#369
b1 %
0!
b0 &
1"
#370
0"
#371
b10 %
b1 &
1"
#372
0"
#373
b11 %
b10 &
1"
#374
0"
#375
b0 %
1!
b11 &
1"
#376
0"
#377
b1 %
0!
b0 &
1"
#378
0"
#379
b10 %
b1 &
1"
#380
0"
#381
b11 %
b10 &
1"
#382
0"
#383
b0 %
1!
b11 &
1"
#384
0"
#385
b1 %
0!
b0 &
1"
#386
0"
#387
b10 %
b1 &
1"
#388
0"
#389
b11 %
b10 &
1"
#390
0"
#391
b0 %
1!
b11 &
1"
#392
0"
#393
b1 %
0!
b0 &
1"
#394
0"
#395
b10 %
b1 &
1"
#396
0"
#397
b11 %
b10 &
1"
#398
0"
#399
b0 %
1!
b11 &
1"
#400
0"
#401
b1 %
0!
b0 &
1"
#402
0"
#403
b10 %
b1 &
1"
#404
0"
#405
b11 %
b10 &
1"
#406
0"
#407
b0 %
1!
b11 &
1"
#408
0"
#409
b1 %
0!
b0 &
1"
#410
0"
#411
b10 %
b1 &
1"
#412
0"
#413
b11 %
b10 &
1"
#414
0"
#415
b0 %
1!
b11 &
1"
#416
0"
#417
b1 %
0!
b0 &
1"
#418
0"
#419
b10 %
b1 &
1"
#420
0"
#421
b11 %
b10 &
1"
#422
0"
#423
b0 %
1!
b11 &
1"
#424
0"
#425
b1 %
0!
b0 &
1"
#426
0"
#427
b10 %
b1 &
1"
#428
0"
#429
b11 %
b10 &
1"
#430
0"
#431
b0 %
1!
b11 &
1"
#432
0"
#433
b1 %
0!
b0 &
1"
#434
0"
#435
b10 %
b1 &
1"
#436
0"
#437
b11 %
b10 &
1"
#438
0"
#439
b0 %
1!
b11 &
1"
#440
0"
#441
b1 %
0!
b0 &
1"
#442
0"
#443
b10 %
b1 &
1"
#444
0"
#445
b11 %
b10 &
1"
#446
0"
#447
b0 %
1!
b11 &
1"
#448
0"
#449
b1 %
0!
b0 &
1"
#450
0"
#451
b10 %
b1 &
1"
#452
0"
#453
b11 %
b10 &
1"
#454
0"
#455
b0 %
1!
b11 &
1"
#456
0"
#457
b1 %
0!
b0 &
1"
#458
0"
#459
b10 %
b1 &
1"
#460
0"
#461
b11 %
b10 &
1"
#462
0"
#463
b0 %
1!
b11 &
1"
#464
0"
#465
b1 %
0!
b0 &
1"
#466
0"
#467
b10 %
b1 &
1"
#468
0"
#469
b11 %
b10 &
1"
#470
0"
#471
b0 %
1!
b11 &
1"
#472
0"
#473
b1 %
0!
b0 &
1"
#474
0"
#475
b10 %
b1 &
1"
#476
0"
#477
b11 %
b10 &
1"
#478
0"
#479
b0 %
1!
b11 &
1"
#480
0"
#481
b1 %
0!
b0 &
1"
#482
0"
#483
b10 %
b1 &
1"
#484
0"
#485
b11 %
b10 &
1"
#486
0"
#487
b0 %
1!
b11 &
1"
#488
0"
#489
b1 %
0!
b0 &
1"
#490
0"
#491
b10 %
b1 &
1"
#492
0"
#493
b11 %
b10 &
1"
#494
0"
#495
b0 %
1!
b11 &
1"
#496
0"
#497
b1 %
0!
b0 &
1"
#498
0"
#499
b10 %
b1 &
1"
#500
0"
#501
b11 %
b10 &
1"
#502
0"
#503
b0 %
1!
b11 &
1"
