verilog001/teste.v
module testbench;

    reg x;

    reg [9:0] num;

    always #1 x <= ~x;

    always #1 num <= num + 1;

    initial begin
        $dumpvars;
        
        x <= 0;
        num <= 0;

        #500;
        $finish;

    end

endmodule

verilog001/dump.vcd
$date
	Mon Jun 20 19:19:20 2022
$end
$version
	Icarus Verilog
$end
$timescale
	1s
$end
$scope module testbench $end
$var reg 10 ! num [9:0] $end
$var reg 1 " x $end
$upscope $end
$enddefinitions $end
$comment Show the parameter values. $end
$dumpall
$end
#0
$dumpvars
0"
b0 !
$end
#1
b1 !
1"
#2
b10 !
0"
#3
b11 !
1"
#4
b100 !
0"
#5
b101 !
1"
#6
b110 !
0"
#7
b111 !
1"
#8
b1000 !
0"
#9
b1001 !
1"
#10
b1010 !
0"
#11
b1011 !
1"
#12
b1100 !
0"
#13
b1101 !
1"
#14
b1110 !
0"
#15
b1111 !
1"
#16
b10000 !
0"
#17
b10001 !
1"
#18
b10010 !
0"
#19
b10011 !
1"
#20
b10100 !
0"
#21
b10101 !
1"
#22
b10110 !
0"
#23
b10111 !
1"
#24
b11000 !
0"
#25
b11001 !
1"
#26
b11010 !
0"
#27
b11011 !
1"
#28
b11100 !
0"
#29
b11101 !
1"
#30
b11110 !
0"
#31
b11111 !
1"
#32
b100000 !
0"
#33
b100001 !
1"
#34
b100010 !
0"
#35
b100011 !
1"
#36
b100100 !
0"
#37
b100101 !
1"
#38
b100110 !
0"
#39
b100111 !
1"
#40
b101000 !
0"
#41
b101001 !
1"
#42
b101010 !
0"
#43
b101011 !
1"
#44
b101100 !
0"
#45
b101101 !
1"
#46
b101110 !
0"
#47
b101111 !
1"
#48
b110000 !
0"
#49
b110001 !
1"
#50
b110010 !
0"
#51
b110011 !
1"
#52
b110100 !
0"
#53
b110101 !
1"
#54
b110110 !
0"
#55
b110111 !
1"
#56
b111000 !
0"
#57
b111001 !
1"
#58
b111010 !
0"
#59
b111011 !
1"
#60
b111100 !
0"
#61
b111101 !
1"
#62
b111110 !
0"
#63
b111111 !
1"
#64
b1000000 !
0"
#65
b1000001 !
1"
#66
b1000010 !
0"
#67
b1000011 !
1"
#68
b1000100 !
0"
#69
b1000101 !
1"
#70
b1000110 !
0"
#71
b1000111 !
1"
#72
b1001000 !
0"
#73
b1001001 !
1"
#74
b1001010 !
0"
#75
b1001011 !
1"
#76
b1001100 !
0"
#77
b1001101 !
1"
#78
b1001110 !
0"
#79
b1001111 !
1"
#80
b1010000 !
0"
#81
b1010001 !
1"
#82
b1010010 !
0"
#83
b1010011 !
1"
#84
b1010100 !
0"
#85
b1010101 !
1"
#86
b1010110 !
0"
#87
b1010111 !
1"
#88
b1011000 !
0"
#89
b1011001 !
1"
#90
b1011010 !
0"
#91
b1011011 !
1"
#92
b1011100 !
0"
#93
b1011101 !
1"
#94
b1011110 !
0"
#95
b1011111 !
1"
#96
b1100000 !
0"
#97
b1100001 !
1"
#98
b1100010 !
0"
#99
b1100011 !
1"
#100
b1100100 !
0"
#101
b1100101 !
1"
#102
b1100110 !
0"
#103
b1100111 !
1"
#104
b1101000 !
0"
#105
b1101001 !
1"
#106
b1101010 !
0"
#107
b1101011 !
1"
#108
b1101100 !
0"
#109
b1101101 !
1"
#110
b1101110 !
0"
#111
b1101111 !
1"
#112
b1110000 !
0"
#113
b1110001 !
1"
#114
b1110010 !
0"
#115
b1110011 !
1"
#116
b1110100 !
0"
#117
b1110101 !
1"
#118
b1110110 !
0"
#119
b1110111 !
1"
#120
b1111000 !
0"
#121
b1111001 !
1"
#122
b1111010 !
0"
#123
b1111011 !
1"
#124
b1111100 !
0"
#125
b1111101 !
1"
#126
b1111110 !
0"
#127
b1111111 !
1"
#128
b10000000 !
0"
#129
b10000001 !
1"
#130
b10000010 !
0"
#131
b10000011 !
1"
#132
b10000100 !
0"
#133
b10000101 !
1"
#134
b10000110 !
0"
#135
b10000111 !
1"
#136
b10001000 !
0"
#137
b10001001 !
1"
#138
b10001010 !
0"
#139
b10001011 !
1"
#140
b10001100 !
0"
#141
b10001101 !
1"
#142
b10001110 !
0"
#143
b10001111 !
1"
#144
b10010000 !
0"
#145
b10010001 !
1"
#146
b10010010 !
0"
#147
b10010011 !
1"
#148
b10010100 !
0"
#149
b10010101 !
1"
#150
b10010110 !
0"
#151
b10010111 !
1"
#152
b10011000 !
0"
#153
b10011001 !
1"
#154
b10011010 !
0"
#155
b10011011 !
1"
#156
b10011100 !
0"
#157
b10011101 !
1"
#158
b10011110 !
0"
#159
b10011111 !
1"
#160
b10100000 !
0"
#161
b10100001 !
1"
#162
b10100010 !
0"
#163
b10100011 !
1"
#164
b10100100 !
0"
#165
b10100101 !
1"
#166
b10100110 !
0"
#167
b10100111 !
1"
#168
b10101000 !
0"
#169
b10101001 !
1"
#170
b10101010 !
0"
#171
b10101011 !
1"
#172
b10101100 !
0"
#173
b10101101 !
1"
#174
b10101110 !
0"
#175
b10101111 !
1"
#176
b10110000 !
0"
#177
b10110001 !
1"
#178
b10110010 !
0"
#179
b10110011 !
1"
#180
b10110100 !
0"
#181
b10110101 !
1"
#182
b10110110 !
0"
#183
b10110111 !
1"
#184
b10111000 !
0"
#185
b10111001 !
1"
#186
b10111010 !
0"
#187
b10111011 !
1"
#188
b10111100 !
0"
#189
b10111101 !
1"
#190
b10111110 !
0"
#191
b10111111 !
1"
#192
b11000000 !
0"
#193
b11000001 !
1"
#194
b11000010 !
0"
#195
b11000011 !
1"
#196
b11000100 !
0"
#197
b11000101 !
1"
#198
b11000110 !
0"
#199
b11000111 !
1"
#200
b11001000 !
0"
#201
b11001001 !
1"
#202
b11001010 !
0"
#203
b11001011 !
1"
#204
b11001100 !
0"
#205
b11001101 !
1"
#206
b11001110 !
0"
#207
b11001111 !
1"
#208
b11010000 !
0"
#209
b11010001 !
1"
#210
b11010010 !
0"
#211
b11010011 !
1"
#212
b11010100 !
0"
#213
b11010101 !
1"
#214
b11010110 !
0"
#215
b11010111 !
1"
#216
b11011000 !
0"
#217
b11011001 !
1"
#218
b11011010 !
0"
#219
b11011011 !
1"
#220
b11011100 !
0"
#221
b11011101 !
1"
#222
b11011110 !
0"
#223
b11011111 !
1"
#224
b11100000 !
0"
#225
b11100001 !
1"
#226
b11100010 !
0"
#227
b11100011 !
1"
#228
b11100100 !
0"
#229
b11100101 !
1"
#230
b11100110 !
0"
#231
b11100111 !
1"
#232
b11101000 !
0"
#233
b11101001 !
1"
#234
b11101010 !
0"
#235
b11101011 !
1"
#236
b11101100 !
0"
#237
b11101101 !
1"
#238
b11101110 !
0"
#239
b11101111 !
1"
#240
b11110000 !
0"
#241
b11110001 !
1"
#242
b11110010 !
0"
#243
b11110011 !
1"
#244
b11110100 !
0"
#245
b11110101 !
1"
#246
b11110110 !
0"
#247
b11110111 !
1"
#248
b11111000 !
0"
#249
b11111001 !
1"
#250
b11111010 !
0"
#251
b11111011 !
1"
#252
b11111100 !
0"
#253
b11111101 !
1"
#254
b11111110 !
0"
#255
b11111111 !
1"
#256
b100000000 !
0"
#257
b100000001 !
1"
#258
b100000010 !
0"
#259
b100000011 !
1"
#260
b100000100 !
0"
#261
b100000101 !
1"
#262
b100000110 !
0"
#263
b100000111 !
1"
#264
b100001000 !
0"
#265
b100001001 !
1"
#266
b100001010 !
0"
#267
b100001011 !
1"
#268
b100001100 !
0"
#269
b100001101 !
1"
#270
b100001110 !
0"
#271
b100001111 !
1"
#272
b100010000 !
0"
#273
b100010001 !
1"
#274
b100010010 !
0"
#275
b100010011 !
1"
#276
b100010100 !
0"
#277
b100010101 !
1"
#278
b100010110 !
0"
#279
b100010111 !
1"
#280
b100011000 !
0"
#281
b100011001 !
1"
#282
b100011010 !
0"
#283
b100011011 !
1"
#284
b100011100 !
0"
#285
b100011101 !
1"
#286
b100011110 !
0"
#287
b100011111 !
1"
#288
b100100000 !
0"
#289
b100100001 !
1"
#290
b100100010 !
0"
#291
b100100011 !
1"
#292
b100100100 !
0"
#293
b100100101 !
1"
#294
b100100110 !
0"
#295
b100100111 !
1"
#296
b100101000 !
0"
#297
b100101001 !
1"
#298
b100101010 !
0"
#299
b100101011 !
1"
#300
b100101100 !
0"
#301
b100101101 !
1"
#302
b100101110 !
0"
#303
b100101111 !
1"
#304
b100110000 !
0"
#305
b100110001 !
1"
#306
b100110010 !
0"
#307
b100110011 !
1"
#308
b100110100 !
0"
#309
b100110101 !
1"
#310
b100110110 !
0"
#311
b100110111 !
1"
#312
b100111000 !
0"
#313
b100111001 !
1"
#314
b100111010 !
0"
#315
b100111011 !
1"
#316
b100111100 !
0"
#317
b100111101 !
1"
#318
b100111110 !
0"
#319
b100111111 !
1"
#320
b101000000 !
0"
#321
b101000001 !
1"
#322
b101000010 !
0"
#323
b101000011 !
1"
#324
b101000100 !
0"
#325
b101000101 !
1"
#326
b101000110 !
0"
#327
b101000111 !
1"
#328
b101001000 !
0"
#329
b101001001 !
1"
#330
b101001010 !
0"
#331
b101001011 !
1"
#332
b101001100 !
0"
#333
b101001101 !
1"
#334
b101001110 !
0"
#335
b101001111 !
1"
#336
b101010000 !
0"
#337
b101010001 !
1"
#338
b101010010 !
0"
#339
b101010011 !
1"
#340
b101010100 !
0"
#341
b101010101 !
1"
#342
b101010110 !
0"
#343
b101010111 !
1"
#344
b101011000 !
0"
#345
b101011001 !
1"
#346
b101011010 !
0"
#347
b101011011 !
1"
#348
b101011100 !
0"
#349
b101011101 !
1"
#350
b101011110 !
0"
#351
b101011111 !
1"
#352
b101100000 !
0"
#353
b101100001 !
1"
#354
b101100010 !
0"
#355
b101100011 !
1"
#356
b101100100 !
0"
#357
b101100101 !
1"
#358
b101100110 !
0"
#359
b101100111 !
1"
#360
b101101000 !
0"
#361
b101101001 !
1"
#362
b101101010 !
0"
#363
b101101011 !
1"
#364
b101101100 !
0"
#365
b101101101 !
1"
#366
b101101110 !
0"
#367
b101101111 !
1"
#368
b101110000 !
0"
#369
b101110001 !
1"
#370
b101110010 !
0"
#371
b101110011 !
1"
#372
b101110100 !
0"
#373
b101110101 !
1"
#374
b101110110 !
0"
#375
b101110111 !
1"
#376
b101111000 !
0"
#377
b101111001 !
1"
#378
b101111010 !
0"
#379
b101111011 !
1"
#380
b101111100 !
0"
#381
b101111101 !
1"
#382
b101111110 !
0"
#383
b101111111 !
1"
#384
b110000000 !
0"
#385
b110000001 !
1"
#386
b110000010 !
0"
#387
b110000011 !
1"
#388
b110000100 !
0"
#389
b110000101 !
1"
#390
b110000110 !
0"
#391
b110000111 !
1"
#392
b110001000 !
0"
#393
b110001001 !
1"
#394
b110001010 !
0"
#395
b110001011 !
1"
#396
b110001100 !
0"
#397
b110001101 !
1"
#398
b110001110 !
0"
#399
b110001111 !
1"
#400
b110010000 !
0"
#401
b110010001 !
1"
#402
b110010010 !
0"
#403
b110010011 !
1"
#404
b110010100 !
0"
#405
b110010101 !
1"
#406
b110010110 !
0"
#407
b110010111 !
1"
#408
b110011000 !
0"
#409
b110011001 !
1"
#410
b110011010 !
0"
#411
b110011011 !
1"
#412
b110011100 !
0"
#413
b110011101 !
1"
#414
b110011110 !
0"
#415
b110011111 !
1"
#416
b110100000 !
0"
#417
b110100001 !
1"
#418
b110100010 !
0"
#419
b110100011 !
1"
#420
b110100100 !
0"
#421
b110100101 !
1"
#422
b110100110 !
0"
#423
b110100111 !
1"
#424
b110101000 !
0"
#425
b110101001 !
1"
#426
b110101010 !
0"
#427
b110101011 !
1"
#428
b110101100 !
0"
#429
b110101101 !
1"
#430
b110101110 !
0"
#431
b110101111 !
1"
#432
b110110000 !
0"
#433
b110110001 !
1"
#434
b110110010 !
0"
#435
b110110011 !
1"
#436
b110110100 !
0"
#437
b110110101 !
1"
#438
b110110110 !
0"
#439
b110110111 !
1"
#440
b110111000 !
0"
#441
b110111001 !
1"
#442
b110111010 !
0"
#443
b110111011 !
1"
#444
b110111100 !
0"
#445
b110111101 !
1"
#446
b110111110 !
0"
#447
b110111111 !
1"
#448
b111000000 !
0"
#449
b111000001 !
1"
#450
b111000010 !
0"
#451
b111000011 !
1"
#452
b111000100 !
0"
#453
b111000101 !
1"
#454
b111000110 !
0"
#455
b111000111 !
1"
#456
b111001000 !
0"
#457
b111001001 !
1"
#458
b111001010 !
0"
#459
b111001011 !
1"
#460
b111001100 !
0"
#461
b111001101 !
1"
#462
b111001110 !
0"
#463
b111001111 !
1"
#464
b111010000 !
0"
#465
b111010001 !
1"
#466
b111010010 !
0"
#467
b111010011 !
1"
#468
b111010100 !
0"
#469
b111010101 !
1"
#470
b111010110 !
0"
#471
b111010111 !
1"
#472
b111011000 !
0"
#473
b111011001 !
1"
#474
b111011010 !
0"
#475
b111011011 !
1"
#476
b111011100 !
0"
#477
b111011101 !
1"
#478
b111011110 !
0"
#479
b111011111 !
1"
#480
b111100000 !
0"
#481
b111100001 !
1"
#482
b111100010 !
0"
#483
b111100011 !
1"
#484
b111100100 !
0"
#485
b111100101 !
1"
#486
b111100110 !
0"
#487
b111100111 !
1"
#488
b111101000 !
0"
#489
b111101001 !
1"
#490
b111101010 !
0"
#491
b111101011 !
1"
#492
b111101100 !
0"
#493
b111101101 !
1"
#494
b111101110 !
0"
#495
b111101111 !
1"
#496
b111110000 !
0"
#497
b111110001 !
1"
#498
b111110010 !
0"
#499
b111110011 !
1"
#500
b111110100 !
0"
